{
  "Diagnostic" : {
    "ICD10" : ["D05", "C50"]
  },

  "Diag_NodalStatus" : {
    "ICD10" : ["C773"]
  },

  "Diag_Proc" : {
    "Breast_core_biopsy" : {
      "CCAM" : ["QEHA001", "QEHA002", "QEHB002", "QEHJ001", "QEHH001", "QEHJ005", "QEHJ006", "QEHH002", "QEHH015", "QEHJ004"]
    },
    "Fine_needle_aspiration_cytology" : {
      "CCAM" : ["QEHB001", "QEHJ002", "QEHJ003", "QEHH003",  "QEHP002"]
    },
    "Breast_Imaging_Procedures" : {
      "Mammograpy" : {
        "CCAM" : ["QEQK001", "QEQK004", "QEQK005"]
        },
      "Mammary_ultrasound" : {
        "CCAM" : ["QEQM001"]
      },
      "Mammary_MRI" : {
          "CCAM" : ["QEQJ001", "QEQN001"]
      },
      "CT_scan" : {
        "CCAM" : ["QEQH002", "QEQK006"]
      },
      "Galactography" : {
          "CCAM" : ["QEQH001"]
      }
    }
  },

  "Surgery_BC": {
    "Surgery" : {
      "CCAM" : ["QEFA003", "QEF005", "QEFA010", "QEFA020", "QEFA007", "QEFA012", "QEFA013", "QEFA015", "QEFA019", "QEFA001", "QEFA008", "QEFA004", "QEFA016", "QEFA017", "QEFA018"]
    },
    "Mastectomy" : {
      "CCAM" : ["QEFA003", "QEF005", "QEFA010", "QEFA020", "QEFA007", "QEFA012", "QEFA013", "QEFA015", "QEFA019"]
    },
    "Partial_Mastectomy" : {
      "CCAM" : ["QEFA001", "QEFA008", "QEFA004", "QEFA016", "QEFA017", "QEFA018"]
    },
    "Mastectomy_with_AxSurg" : {
      "CCAM" : ["QEFA003", "QEF005", "QEFA010", "QEFA020"]
    },
    "Mastectomy_without_AxSurg" : {
      "CCAM" : ["QEFA007", "QEFA012", "QEFA013", "QEFA015", "QEFA019"]
    },
    "Partial_Mastectomy_with_AxSurg" : {
      "CCAM" : ["QEFA001", "QEFA008"]
    },
    "Partial_Mastectomy_without_AxSurg" : {
      "CCAM" : ["QEFA004", "QEFA016", "QEFA017", "QEFA018"]
    },
    "Axillary_Surgery" : {
      "CCAM" : ["QEFA003", "QEF005", "QEFA010", "QEFA020", "FCFA021", "FCFA029"]
    }
  },

  "RT": {
    "ICD10": ["Z5100", "Z5101"],
    "CCAM": ["ZZNA002", "ZZNL001", "ZZNL002", "ZZNL003", "ZZNL004", "ZZNL005", "ZZNL006", "ZZNL009", "ZZNL011", "ZZNL012", "ZZNL013", "ZZNL014", "ZZNL015", "ZZNL016", "ZZNL017", "ZZNL018", "ZZNL019", "ZZNL02", "ZZNL030", "ZZNL031", "ZZNL036", "ZZNL037", "ZZNL039", "ZZNL040", "ZZNL042", "ZZNL043", "ZZNL045", "ZZNL046", "ZZNL048", "ZZNL049", "ZZNL050", "ZZNL051", "ZZNL052", "ZZNL053", "ZZNL054", "ZZNL055", "ZZNL058", "ZZNL059", "ZZNL060", "ZZNL061", "ZZNL062", "ZZNL063", "ZZNL064", "ZZNL065", "ZZNL900", "ZZNL902", "ZZNL903", "ZZNL904", "ZZNL905", "ZZNL906", "YYYY016", "YYYY021", "YYYY023", "YYYY045", "YYYY046", "YYYY047", "YYYY048", "YYYY049", "YYYY050", "YYYY051", "YYYY052", "YYYY053", "YYYY054", "YYYY055", "YYYY056", "YYYY080", "YYYY081", "YYYY099", "YYYY101", "YYYY109", "YYYY122", "YYYY128", "YYYY136", "YYYY141", "YYYY151", "YYYY152", "YYYY166", "YYYY175", "YYYY197", "YYYY1211", "YYYY223", "YYYY225", "YYYY244", "YYYY256", "YYYY267", "YYYY299", "YYYY301", "YYYY302", "YYYY303", "YYYY304", "YYYY305", "YYYY306", "YYYY307", "YYYY310", "YYYY312", "YYYY313", "YYYY314", "YYYY315", "YYYY316", "YYYY320", "YYYY323", "YYYY324", "YYYY325", "YYYY326", "YYYY327", "YYYY331", "YYYY334", "YYYY335", "YYYY336", "YYYY337", "YYYY338", "YYYY343", "YYYY345", "YYYY346", "YYYY347", "YYYY348", "YYYY349", "YYYY356", "YYYY357", "YYYY358", "YYYY359", "YYYY360", "YYYY365", "YYYY367", "YYYY368", "YYYY369", "YYYY370", "YYYY371", "YYYY377", "YYYY379", "YYYY380", "YYYY381", "YYYY382", "YYYY383", "YYYY387", "YYYY390", "YYYY391", "YYYY392", "YYYY393", "YYYY398", "YYYY450", "YYYY451", "YYYY457", "YYYY458", "YYYY459", "YYYY460", "YYYY468", "YYYY469", "YYYY470", "YYYY471", "YYYY479", "YYYY480", "YYYY481", "YYYY491", "YYYY492", "YYYY493", "YYYY497", "YYYY500", "YYYY511", "YYYY520", "YYYY522", "YYYY533", "YYYY544", "YYYY555", "YYYY566", "YYYY577", "YYYY588", "YYYY599"]
  },

  "CT": {
    "ICD10": ["Z511"],
    "CCAM": ["ZZLF900", "EBLA001", "ABLB006", "AFLB003", "AFLB013", "ECLF005", "ECLF006", "EELF004", "EELF005" ,"EDLF014", "EDLF015", "EDLF016", "EDLF017" ,"EDLF018", "EDLF019", "EDLF020", "EDLF021", "EBLF002", "EBLF003", "GGLB001", "GGLB008", "HPLB002", "HPLB003", "HPLB007", "ZZLF004", "ZZLF900"],
    "ATC": ["L01AA01", "L01CD02", "L01DB03", "L01BC02", "L01CD01"],
    "UCD": ["9031083", "9031077", "9031114", "9178082", "9178099", "9145332", "9145361", "9284306", "9284312", "9284329", "9284335", "9284341", "9284358", "9284364", "9284370", "9284387", "9284393", "9284401", "9284418", "9284424", "9285257", "9285263", "9285286", "9285292", "9285300", "9285317", "9285323", "9285346", "9285352", "9293357", "9293363", "9293386", "9293392", "9304457", "9304463", "9304486", "9304492", "9305095", "9305103", "9305126", "9305132", "9306605", "9306611", "9306628", "9306634", "9306640", "9306657", "9306663", "9306686", "9313137", "9313143", "9313166", "9313172", "9313189", "9316058", "9316064", "9316070", "9319708", "9319714", "9328481", "9332637", "9332643", "9337913", "9337936", "9337942", "9337959", "9343724", "9343730", "9343747", "9343753", "9224505", "9030534", "9224505", "9303995", "9191527", "9191533", "9191556", "9192107", "9192113", "9192136", "9196163", "9196186", "9196192", "9196200", "9216925", "9227685", "9227691", "9227716", "9227722", "9247191", "9247216", "9247222", "9247239", "9257315", "9268276", "9268282", "9334866", "9334872", "9334889", "9334895", "9340950", "9340967", "9340973", "9340996", "9341004", "9278091", "9278116", "9278122", "9282744", "9282750", "9282767", "9282773", "9284499", "9284507", "9284513", "9284536", "9285381", "9285398", "9285406", "9285412", "9290459", "9290465", "9290471", "9296829", "9296835", "9296841", "9296858", "9299443", "9299466", "9299472", "9299489", "9305379", "9305385", "9305391", "9308254", "9308923", "9308946", "9308952", "9308969", "9319022", "9327903", "9327926", "9327932", "9327949", "9332809", "9332815", "9332821", "9363282", "9363299", "9363307", "9366441", "9366458", "9401350", "9401367"]
  },

  "TT": {
    "Trastuzumab" : {
      "ATC"  :  ["L01XC13", "L01XC14"]
    },
    "Pertuzumab" : {
      "ATC" : ["L01XC03"],
      "CIP13" : ["3400938379457", "3400938379518", "3400941701764", "3400941701825", "3400941701993", "3400949164349"],
      "UCD" : ["9220097", "9400037"]
     }
  },

  "ET": {
    "Tamoxifen" : {
      "ATC" : ["L02BA01"],
      "CIP13" : ["3400932059324", "3400932865284", "3400932903467", "3400932903696", "3400932921508", "3400932921737", "3400933179441", "3400933263867", "3400933263928", "3400933288303", "3400933430542", "3400933952235", "3400933952464", "3400934106323", "3400934106491", "3400934303623", "3400934303791", "3400934317811", "3400934639302", "3400934639470", "3400934639531", "3400935646316", "3400935646484", "3400935795908", "3400935825407", "3400935833440", "3400935940230", "3400935940469", "3400936136540", "3400936136601", "3400936143463", "3400936143524", "3400936143692", "3400936476189", "3400936476240", "3400936663954", "3400936664036", "3400936797598", "3400936797659"]
    },
    "Aromatase_Inhibitor" : {
      "ATC" : ["LO2BG03", "L02BG06", "L02BG04"],
      "CIP13" : ["3400921636116", "3400921654783", "3400921792102", "3400921997507", "3400922133263", "3400922133324", "3400922136165", "3400922136455", "3400922211428", "3400930108338", "3400930108345", "3400930117248", "3400930162309", "3400934147425", "3400934236464", "3400934236525", "3400934625923", "3400934626234", "3400934712081", "3400935279668", "3400935901149", "3400935901897", "3400935985354", "3400935985415", "3400936037625", "3400938276749", "3400938294088", "3400938434378", "3400938434439", "3400938435030", "3400938435610", "3400938436150", "3400938436679", "3400938515084", "3400938515145", "3400938515664", "3400938943054", "3400939095219", "3400939161365", "3400939259802", "3400939331751", "3400939413709", "3400939413877", "3400939439372", "3400939664538", "3400939665078", "3400939665368", "3400939665429", "3400939764634", "3400939851952", "3400939986609", "3400939986838", "3400939987378", "3400939987668", "3400939987958", "3400939988030", "3400939988320", "3400941509377", "3400941519314", "3400941520204", "3400941553899", "3400941554490", "3400941557392", "3400941627682", "3400941677779", "3400941950124", "3400941950414", "3400949000029", "3400949000401", "3400949000487", "3400949000647", "3400949000784", "3400949000937", "3400949000944", "3400949001859", "3400949001958", "3400949001972", "3400949002139", "3400949003150", "3400949004911", "3400949008292", "3400949011483", "3400949013845", "3400949015627", "3400949016167", "3400949017348", "3400949017577", "3400949019939", "3400949020188", "3400949027743", "3400949140855", "3400949185801", "3400949188123", "3400949190133", "3400949205592", "3400949248537", "3400949252619", "3400949275670", "3400949275731", "3400949276332", "3400949277162", "3400949277513", "3400949277681", "3400949295371", "3400949410019", "3400949410248", "3400949410477", "3400949452460", "3400949497294", "3400949497706", "3400949626359", "3400949630950", "3400949640836", "3400949855827", "3400949881789", "3400949882151", "3400949916542", "3400949931859", "3400949980994", "3400949982028"]
    },
    "GnRH_agonists" : {
      "ATC" : ["L02AE03", "L02AE02", "L02AE04"],
      "CIP13" : ["3400930020005", "3400930122112", "3400930122129", "3400932829217", "3400932850037", "3400932850266", "3400932932672", "3400933129125", "3400933943769", "3400933963811", "3400934125423", "3400934125652", "3400935844675", "3400936690868", "3400936690929", "3400937575256", "3400937575317", "3400938081459", "3400938263381", "3400938458381", "3400939262123", "3400939890173", "3400949002634", "3400949002818"]
    },
    "All" : {
      "CIP13" : ["3400932059324", "3400932865284", "3400932903467", "3400932903696", "3400932921508", "3400932921737", "3400933179441", "3400933263867", "3400933263928", "3400933288303", "3400933430542", "3400933952235", "3400933952464", "3400934106323", "3400934106491", "3400934303623", "3400934303791", "3400934317811", "3400934639302", "3400934639470", "3400934639531", "3400935646316", "3400935646484", "3400935795908", "3400935825407", "3400935833440", "3400935940230", "3400935940469", "3400936136540", "3400936136601", "3400936143463", "3400936143524", "3400936143692", "3400936476189", "3400936476240", "3400936663954", "3400936664036", "3400936797598", "3400936797659", "3400921636116", "3400921654783", "3400921792102", "3400921997507", "3400922133263", "3400922133324", "3400922136165", "3400922136455", "3400922211428", "3400930108338", "3400930108345", "3400930117248", "3400930162309", "3400934147425", "3400934236464", "3400934236525", "3400934625923", "3400934626234", "3400934712081", "3400935279668", "3400935901149", "3400935901897", "3400935985354", "3400935985415", "3400936037625", "3400938276749", "3400938294088", "3400938434378", "3400938434439", "3400938435030", "3400938435610", "3400938436150", "3400938436679", "3400938515084", "3400938515145", "3400938515664", "3400938943054", "3400939095219", "3400939161365", "3400939259802", "3400939331751", "3400939413709", "3400939413877", "3400939439372", "3400939664538", "3400939665078", "3400939665368", "3400939665429", "3400939764634", "3400939851952", "3400939986609", "3400939986838", "3400939987378", "3400939987668", "3400939987958", "3400939988030", "3400939988320", "3400941509377", "3400941519314", "3400941520204", "3400941553899", "3400941554490", "3400941557392", "3400941627682", "3400941677779", "3400941950124", "3400941950414", "3400949000029", "3400949000401", "3400949000487", "3400949000647", "3400949000784", "3400949000937", "3400949000944", "3400949001859", "3400949001958", "3400949001972", "3400949002139", "3400949003150", "3400949004911", "3400949008292", "3400949011483", "3400949013845", "3400949015627", "3400949016167", "3400949017348", "3400949017577", "3400949019939", "3400949020188", "3400949027743", "3400949140855", "3400949185801", "3400949188123", "3400949190133", "3400949205592", "3400949248537", "3400949252619", "3400949275670", "3400949275731", "3400949276332", "3400949277162", "3400949277513", "3400949277681", "3400949295371", "3400949410019", "3400949410248", "3400949410477", "3400949452460", "3400949497294", "3400949497706", "3400949626359", "3400949630950", "3400949640836", "3400949855827", "3400949881789", "3400949882151", "3400949916542", "3400949931859", "3400949980994", "3400949982028", "3400930020005", "3400930122112", "3400930122129", "3400932829217", "3400932850037", "3400932850266", "3400932932672", "3400933129125", "3400933943769", "3400933963811", "3400934125423", "3400934125652", "3400935844675", "3400936690868", "3400936690929", "3400937575256", "3400937575317", "3400938081459", "3400938263381", "3400938458381", "3400939262123", "3400939890173", "3400949002634", "3400949002818"]
    }
  },


  "Diag_Metastatic": {
    "ICD10" : ["C770", "C771", "C772", "C774", "C775", "C778", "C779", "C78", "C780", "C781", "C782", "C783", "C784", "C785", "C786", "C787", "C788", "C79", "C790", "C791", "C792", "C793", "C794", "C795", "C796", "C797", "C798", "C799"]
  },

  "CT_Metastatic": {
    "ATC" : ["L01BC06", "L01XA02", "L01XA01", "L01DB01", "L01XX41", "L01CB01", "L01BC05", "L01AA03", "L01BA01", "L01XX09", "L01DC03", "L01DB07", "L01DB08", "L01AC01", "L01CA01", "L01CA02", "L01CA03", "L01CA04"]
  },

  "TT_Metastatic" : {
    "HER2" : {
      "ATC" : ["L01XE07"]
    },
    "Non_HER2" : {
      "ATC" : ["L01XC07", "L01XE", "L01XE10", "L01XE33"]
    }
  },

  "ET_Metastatic" : {
    "ATC" : ["L02BA02", "L02BG02", "L02BA03"]
  },

  "Other_treatments_Metastatic" : {
    "ATC": [ "V03AF02", "V10BX02"]
  }
}
  
